{
    "$schema": "https://schema.management.azure.com/schemas/2015-01-01/deploymentParameters.json#",
    "contentVersion": "1.0.0.0",
    "parameters": {
        "clusterName": {
            "value": "enialrash"
        },
        "location": {
            "value": "southeastasia" 
        },
        "virtualMachineSize": {
            "value": "Standard_D3_v2"
        },
        "diskSize": {
            "value": 50
        },
        "adminUsername": {
            "value": "enialrash"
        },
        "adminPublicKey": {
            "value": "ssh-rsa *** user@desktop"
        }
    }
}